LICENSE
MANIFEST.in
README.md
requirements.txt
setup.cfg
setup.py
conf_publisher/__init__.py
conf_publisher/auth.py
conf_publisher/config.py
conf_publisher/confluence.py
conf_publisher/confluence_api.py
conf_publisher/constants.py
conf_publisher/errors.py
conf_publisher/page_dumper.py
conf_publisher/page_maker.py
conf_publisher/publish.py
conf_publisher/data_providers/__init__.py
conf_publisher/data_providers/sphinx_base_data_provider.py
conf_publisher/data_providers/sphinx_fjson_data_provider.py
conf_publisher/data_providers/sphinx_html_data_provider.py
conf_publisher/mutators/__init__.py
conf_publisher/mutators/page_mutator.py
conf_publisher/serializers/__init__.py
conf_publisher/serializers/json_serializer.py
conf_publisher/serializers/yaml_serializer.py
confluence_publisher_ex.egg-info/PKG-INFO
confluence_publisher_ex.egg-info/SOURCES.txt
confluence_publisher_ex.egg-info/dependency_links.txt
confluence_publisher_ex.egg-info/entry_points.txt
confluence_publisher_ex.egg-info/requires.txt
confluence_publisher_ex.egg-info/top_level.txt