Metadata-Version: 1.1
Name: confluence-publisher-ex
Version: 1.1.0
Summary: Tool for publishing Sphinx generated documents to Confluence
Home-page: https://github.com/marooou/confluence-publisher
Author: Marek Chmiel
Author-email: UNKNOWN
License: MIT
Platform: UNKNOWN
Classifier: Development Status :: 4 - Beta
Classifier: Environment :: Console
Classifier: Intended Audience :: Developers
Classifier: License :: OSI Approved :: MIT License
Classifier: Operating System :: OS Independent
Classifier: Programming Language :: Python :: 2.7
Classifier: Programming Language :: Python :: 3.3
Classifier: Programming Language :: Python :: 3.4
Classifier: Programming Language :: Python :: 3.5
Classifier: Topic :: Software Development :: Documentation
